jonson/__init__.py
jonson-1.1.1.dist-info/LICENSE
jonson-1.1.1.dist-info/METADATA
jonson-1.1.1.dist-info/WHEEL
jonson-1.1.1.dist-info/top_level.txt
jonson-1.1.1.dist-info/RECORD
