Metadata-Version: 2.1
Name: jonson
Version: 1.1.1
Summary: out-of-the-box, ready-to-use JSON logger
Home-page: https://github.com/omrilotan/jonson
Author: omrilotan
License: unlicense
Keywords: json,logger,structured logging
Classifier: Programming Language :: Python
Classifier: Operating System :: OS Independent
Requires-Python: >=3
License-File: LICENSE
